LICENSE
README.md
setup.py
arjun/__init__.py
arjun/__main__.py
arjun.egg-info/PKG-INFO
arjun.egg-info/SOURCES.txt
arjun.egg-info/dependency_links.txt
arjun.egg-info/entry_points.txt
arjun.egg-info/not-zip-safe
arjun.egg-info/requires.txt
arjun.egg-info/top_level.txt
arjun/core/__init__.py
arjun/core/anomaly.py
arjun/core/bruter.py
arjun/core/colors.py
arjun/core/config.py
arjun/core/error_handler.py
arjun/core/exporter.py
arjun/core/importer.py
arjun/core/prompt.py
arjun/core/requester.py
arjun/core/utils.py
arjun/db/large.txt
arjun/db/medium.txt
arjun/db/small.txt
arjun/db/special.json
arjun/plugins/__init__.py
arjun/plugins/commoncrawl.py
arjun/plugins/heuristic.py
arjun/plugins/otx.py
arjun/plugins/wayback.py
arjun/plugins/wl.py