Metadata-Version: 2.1
Name: arjun
Version: 2.2.7
Summary: HTTP parameter discovery suite
Home-page: https://github.com/s0md3v/Arjun
Download-URL: https://github.com/s0md3v/Arjun/archive/v2.2.7.zip
Author: Somdev Sangwan
Author-email: s0md3v@gmail.com
License: GNU General Public License v3 (GPLv3)
Keywords: arjun,bug bounty,http,pentesting,security
Classifier: Development Status :: 5 - Production/Stable
Classifier: Intended Audience :: Developers
Classifier: Intended Audience :: Information Technology
Classifier: Operating System :: OS Independent
Classifier: Topic :: Security
Classifier: License :: OSI Approved :: GNU Affero General Public License v3
Classifier: Programming Language :: Python :: 3.4
License-File: LICENSE
Requires-Dist: requests
Requires-Dist: dicttoxml
Requires-Dist: ratelimit
